RTL/IF/pc.v
module pc (
    input wire clk,
    input wire reset,
    input wire [31:0] pc_next,
    output reg [31:0] pc
);

always @(posedge clk or posedge reset) begin
    if (reset)
        pc <= 32'b0;
    else
        pc <= pc_next;
end

endmodule

Testbench/pc_tb.v
`timescale 1ns/1ps

module pc_tb;

    reg clk;
    reg reset;
    reg [31:0] pc_next;

    wire [31:0] pc;

    // Instantiate the Program Counter
    pc uut (
        .clk(clk),
        .reset(reset),
        .pc_next(pc_next),
        .pc(pc)
    );

    // Clock generation (10 ns period)
    always #5 clk = ~clk;

    initial begin

        // Generate VCD waveform file
        $dumpfile("pc.vcd");
        $dumpvars(0, pc_tb);

        // Initial values
        clk = 0;
        reset = 1;
        pc_next = 32'd0;

        // Hold reset for 10 ns
        #10;
        reset = 0;

        // Apply PC values
        #10 pc_next = 32'd4;
        #10 pc_next = 32'd8;
        #10 pc_next = 32'd12;
        #10 pc_next = 32'd16;
        #10 pc_next = 32'd20;

        // Wait before finishing
        #20;

        $finish;
    end

endmodule

pc.vcd
$date
	Wed Jul 01 00:03:14 2026
$end
$version
	Icarus Verilog
$end
$timescale
	1ps
$end
$scope module pc_tb $end
$var wire 32 ! pc [31:0] $end
$var reg 1 " clk $end
$var reg 32 # pc_next [31:0] $end
$var reg 1 $ reset $end
$scope module uut $end
$var wire 1 " clk $end
$var wire 32 % pc_next [31:0] $end
$var wire 1 $ reset $end
$var reg 32 & pc [31:0] $end
$upscope $end
$upscope $end
$enddefinitions $end
$comment Show the parameter values. $end
$dumpall
$end
#0
$dumpvars
b0 &
b0 %
1$
b0 #
0"
b0 !
$end
#5000
1"
#10000
0"
0$
#15000
1"
#20000
0"
b100 #
b100 %
#25000
b100 !
b100 &
1"
#30000
0"
b1000 #
b1000 %
#35000
b1000 !
b1000 &
1"
#40000
0"
b1100 #
b1100 %
#45000
b1100 !
b1100 &
1"
#50000
0"
b10000 #
b10000 %
#55000
b10000 !
b10000 &
1"
#60000
0"
b10100 #
b10100 %
#65000
b10100 !
b10100 &
1"
